{
  "schemaVersion": 1,
  "asOf": "2026-07-15",
  "generatedAt": "2026-07-15T08:19:27.821Z",
  "status": {
    "isPartial": false,
    "message": "所有风险模型数据源已成功更新。",
    "sources": {
      "fred": {
        "ok": true,
        "partial": false,
        "updatedAt": "2026-07-15T08:19:27.821Z",
        "message": "更新成功",
        "succeeded": [
          "VIX (VIXCLS)",
          "ICE BofA US High Yield Spread (BAMLH0A0HYM2)",
          "10Y Treasury Yield (DGS10)",
          "2Y Treasury Yield (DGS2)",
          "S&P 500 (SP500)",
          "Nasdaq 100 (NASDAQ100)"
        ],
        "failed": []
      },
      "yahoo": {
        "ok": true,
        "partial": false,
        "updatedAt": "2026-07-15T08:19:27.821Z",
        "message": "更新成功",
        "succeeded": [
          "VIX (^VIX)"
        ],
        "failed": []
      },
      "treasury": {
        "ok": true,
        "partial": false,
        "updatedAt": "2026-07-15T08:19:27.821Z",
        "message": "更新成功",
        "succeeded": [
          "10Y Treasury",
          "2Y Treasury"
        ],
        "failed": []
      },
      "fallback": {
        "ok": true,
        "partial": false,
        "updatedAt": "2026-07-15T08:19:27.821Z",
        "message": "本次未触发",
        "succeeded": [],
        "failed": []
      }
    }
  },
  "riskScore": 39,
  "weightedZ": -0.45,
  "rawWeightedZ": -0.45,
  "crisisFlag": false,
  "crisisReason": "未触发危机级条件，rawWeightedRiskZ=-0.45",
  "riskLevel": "贪婪",
  "posture": "偏进攻",
  "factors": [
    {
      "id": "volatility",
      "name": "波动率风险",
      "source": "FRED: VIXCLS",
      "rawValue": 16.34,
      "rawDisplay": "16.34",
      "rawStdDev": 3.3088,
      "benchmarkValue": 18.0948,
      "benchmarkDisplay": "18.09",
      "benchmarkLabel": "250日均值",
      "riskValue": 16.34,
      "riskBenchmarkValue": 18.0948,
      "riskStdDev": 3.3088,
      "rawZScore": -0.53,
      "clippedZScore": -0.53,
      "zScore": -0.53,
      "weight": 0.25,
      "contribution": -0.13,
      "riskLevel": "低风险",
      "progress": 37,
      "trend": "down",
      "window": "250 个交易日",
      "windowDays": 250,
      "note": "VIX 越高，市场隐含波动与避险需求越高。",
      "manualLabel": "VIX",
      "manualUnit": "",
      "manualStep": 0.01,
      "date": "2026-07-15",
      "stale": false
    },
    {
      "id": "credit",
      "name": "信用风险",
      "source": "FRED: BAMLH0A0HYM2",
      "rawValue": 2.69,
      "rawDisplay": "2.69%",
      "rawStdDev": 0.1593,
      "benchmarkValue": 2.8896,
      "benchmarkDisplay": "2.89%",
      "benchmarkLabel": "250日均值",
      "riskValue": 2.69,
      "riskBenchmarkValue": 2.8896,
      "riskStdDev": 0.1593,
      "rawZScore": -1.25,
      "clippedZScore": -1.25,
      "zScore": -1.25,
      "weight": 0.25,
      "contribution": -0.31,
      "riskLevel": "低风险",
      "progress": 22,
      "trend": "flat",
      "window": "250 个交易日",
      "windowDays": 250,
      "note": "高收益债利差越宽，信用压力与融资风险越高。",
      "manualLabel": "高收益债利差",
      "manualUnit": "%",
      "manualStep": 0.01,
      "date": "2026-07-13",
      "stale": false
    },
    {
      "id": "yieldCurve",
      "name": "收益率曲线风险",
      "source": "FRED: DGS10 - DGS2",
      "rawValue": 40,
      "rawDisplay": "+40 bp",
      "rawStdDev": 9.6028,
      "benchmarkValue": 54.184,
      "benchmarkDisplay": "+54 bp",
      "benchmarkLabel": "250日均值",
      "riskValue": -40,
      "riskBenchmarkValue": -54.184,
      "riskStdDev": 9.6028,
      "rawZScore": 1.48,
      "clippedZScore": 1.48,
      "zScore": 1.48,
      "weight": 0.15,
      "contribution": 0.22,
      "riskLevel": "极高风险",
      "progress": 81,
      "trend": "down",
      "window": "250 个交易日",
      "windowDays": 250,
      "note": "10Y-2Y 利差越低、倒挂越深，周期压力越高。",
      "manualLabel": "10Y - 2Y 利差",
      "manualUnit": "bp",
      "manualStep": 1,
      "date": "2026-07-14",
      "stale": false
    },
    {
      "id": "trend",
      "name": "趋势风险",
      "source": "FRED: SP500 相对 200日均线",
      "rawValue": 8.17,
      "rawDisplay": "+8.17%",
      "rawStdDev": 3.547,
      "benchmarkValue": 5.9702,
      "benchmarkDisplay": "+5.97%",
      "benchmarkLabel": "120日均值",
      "riskValue": -8.17,
      "riskBenchmarkValue": -5.9702,
      "riskStdDev": 3.547,
      "rawZScore": -0.62,
      "clippedZScore": -0.62,
      "zScore": -0.62,
      "weight": 0.15,
      "contribution": -0.09,
      "riskLevel": "低风险",
      "progress": 35,
      "trend": "down",
      "window": "120 个交易日",
      "windowDays": 120,
      "note": "指数跌破 200日均线越多，趋势风险越高。",
      "manualLabel": "SPX 相对 200MA",
      "manualUnit": "%",
      "manualStep": 0.01,
      "date": "2026-07-14",
      "stale": false
    },
    {
      "id": "momentum",
      "name": "动能风险",
      "source": "FRED: SP500 50日均线斜率",
      "rawValue": 2.75,
      "rawDisplay": "+2.75%",
      "rawStdDev": 2.0839,
      "benchmarkValue": 1.3578,
      "benchmarkDisplay": "+1.36%",
      "benchmarkLabel": "120日均值",
      "riskValue": -2.75,
      "riskBenchmarkValue": -1.3578,
      "riskStdDev": 2.0839,
      "rawZScore": -0.67,
      "clippedZScore": -0.67,
      "zScore": -0.67,
      "weight": 0.2,
      "contribution": -0.13,
      "riskLevel": "低风险",
      "progress": 34,
      "trend": "up",
      "window": "120 个交易日",
      "windowDays": 120,
      "note": "50日均线斜率越弱，市场动能风险越高。",
      "manualLabel": "50MA 斜率",
      "manualUnit": "%",
      "manualStep": 0.01,
      "date": "2026-07-14",
      "stale": false
    }
  ],
  "indices": {
    "sp500": {
      "name": "标普500",
      "ticker": "SPX",
      "levelDisplay": "7,543.59",
      "level": 7543.59,
      "previous": 7515.34,
      "change": 28.25,
      "changePercent": 0.38,
      "distanceDisplay": "+8.17%",
      "distanceTo200Ma": 8.17,
      "note": "位于 200日均线上方",
      "source": "FRED: SP500",
      "date": "2026-07-14",
      "stale": false
    },
    "nasdaq100": {
      "name": "纳斯达克100",
      "ticker": "NDX",
      "levelDisplay": "29,586.29",
      "level": 29586.29,
      "previous": 29264.1,
      "change": 322.19,
      "changePercent": 1.1,
      "distanceDisplay": "+12.63%",
      "distanceTo200Ma": 12.63,
      "note": "位于 200日均线上方",
      "source": "FRED: NASDAQ100",
      "date": "2026-07-14",
      "stale": false
    }
  },
  "summary": "当前市场温度为 39/100，处于贪婪区间。主要风险贡献来自信用、收益率曲线、波动率。该模型面向长期指数配置和逆向定投参考，强调分批执行、现金流稳定与风险纪律，不构成短线交易信号。",
  "model": {
    "formula": "clippedWeightedRiskZ = 0.25×VIX_z + 0.25×Credit_z + 0.15×YieldCurve_z + 0.15×Trend_z + 0.20×Momentum_z",
    "normalization": "RiskScore = crisisFlag ? 100 : min(99, max(1, round(50 + 50 × tanh(clippedWeightedRiskZ / 2))))",
    "scoreMapping": "0-20 极度贪婪；20-40 贪婪；40-60 中性；60-75 恐慌；75-90 高恐慌；90-97 极度恐慌；97-100 危机级恐慌",
    "dataFrequency": "上一交易日收盘数据，每日由 GitHub Actions 自动更新"
  }
}
